{"guid":"root________","title":"","index":0,"dateAdded":1631588948409000,"lastModified":1701932550185000,"id":1,"typeCode":2,"type":"text/x-moz-place-container","root":"placesRoot","children":[{"guid":"menu________","title":"menu","index":0,"dateAdded":1676863722919000,"lastModified":1701932550185000,"id":2,"typeCode":2,"type":"text/x-moz-place-container","root":"bookmarksMenuFolder","children":[{"guid":"3QH-nFzpDk_2","title":"ЖКХ","index":0,"dateAdded":1647742773003000,"lastModified":1699946196489000,"id":7,"typeCode":2,"type":"text/x-moz-place-container","children":[{"guid":"dOvPAQVDozf2","title":"Личный кабинет","index":0,"dateAdded":1647742837151000,"lastModified":1647742864833000,"id":8,"typeCode":1,"iconUri":"https://lk.billing74.ru/resources/img/favicon.ico","type":"text/x-moz-place","uri":"https://lk.billing74.ru/login"},{"guid":"x2uiDuwxclfJ","title":"Электороэнергия","index":1,"dateAdded":1647744282002000,"lastModified":1647745021537000,"id":9,"typeCode":1,"iconUri":"https://lk.esk-ural.ru/favicon.ico?","type":"text/x-moz-place","uri":"https://lk.esk-ural.ru/login"},{"guid":"UlG4MJeTbpPf","title":"Гис ЖКХ","index":2,"dateAdded":1647744847356000,"lastModified":1647745027324000,"id":10,"typeCode":1,"iconUri":"https://dom.gosuslugi.ru/assets/img/favicon.ico","type":"text/x-moz-place","uri":"https://dom.gosuslugi.ru/#!/main"},{"guid":"kKmu-dkG3i9e","title":"Система Город","index":3,"dateAdded":1647744938764000,"lastModified":1647745029561000,"id":11,"typeCode":1,"type":"text/x-moz-place","uri":"https://gorod74.ru/"},{"guid":"IA2jlajI7SY3","title":"АО РИР","index":4,"dateAdded":1647744147997000,"lastModified":1647744214113000,"id":12,"typeCode":1,"type":"text/x-moz-place","uri":"https://rosatom-teplo.ru/ozersk"},{"guid":"XXKXnjDqs4rV","title":"Налоговая служба","index":5,"dateAdded":1663557001298000,"lastModified":1663557093530000,"id":13,"typeCode":1,"iconUri":"https://www.nalog.gov.ru/css/ul2018/img/favicon.ico","type":"text/x-moz-place","uri":"https://www.nalog.gov.ru/rn74/"},{"guid":"JQ-z-QTm3Izv","title":"Пенсионный фонд","index":6,"dateAdded":1663557049550000,"lastModified":1663557059884000,"id":14,"typeCode":1,"type":"text/x-moz-place","uri":"https://pfr.gov.ru/"},{"guid":"JqS14d8LaeKZ","title":"ММПКХ","index":7,"dateAdded":1676863722919000,"lastModified":1676863735127000,"id":15,"typeCode":1,"iconUri":"https://ozerskres.ru/sites/default/files/mmpkxicon2_2.png","type":"text/x-moz-place","uri":"https://ozerskres.ru/"},{"guid":"TTCI_lAdzXS-","title":"Портал государственных услуг","index":8,"dateAdded":1699946196489000,"lastModified":1699946225009000,"id":147,"typeCode":1,"iconUri":"https://gu-st.ru/portal-st/favicon.svg?ver=1.1","type":"text/x-moz-place","uri":"https://www.gosuslugi.ru/"}]},{"guid":"0dKyfr64-LvS","title":"Литра","index":1,"dateAdded":1627452164517000,"lastModified":1701932486050000,"id":16,"typeCode":2,"type":"text/x-moz-place-container","children":[{"guid":"mHSUfS8shmBZ","title":"Флибуста","index":0,"dateAdded":1627452185054000,"lastModified":1627452196736000,"id":17,"typeCode":1,"type":"text/x-moz-place","uri":"http://flibusta.is/"},{"guid":"vb3N1VcA4rXq","title":"Либрусек","index":1,"dateAdded":1686985294037000,"lastModified":1686989285275000,"id":130,"typeCode":1,"iconUri":"http://lib.rus.ec/sites/default/files/favicon.ico","type":"text/x-moz-place","uri":"http://lib.rus.ec/"},{"guid":"9HPmmlvJxOGj","title":"Книги YandexTTS","index":2,"dateAdded":1627614517669000,"lastModified":1627614537794000,"id":18,"typeCode":1,"iconUri":"https://cloud.imgsmail.ru/cloud.mail.ru/206934/img/build/favicon.svg","type":"text/x-moz-place","uri":"https://cloud.mail.ru/public/LcQN/CCvMnyp7N/"},{"guid":"hJvWeN_7OzW9","title":"Play_5А","index":3,"dateAdded":1627614620450000,"lastModified":1627614629447000,"id":19,"typeCode":1,"iconUri":"https://cloud.imgsmail.ru/cloud.mail.ru/206934/img/build/favicon.svg","type":"text/x-moz-place","uri":"https://cloud.mail.ru/public/GZDh/2QnTQfMwp/"},{"guid":"592QJquPLEuq","title":"MyTTS","index":4,"dateAdded":1631165294417000,"lastModified":1652596813794000,"id":20,"typeCode":1,"type":"text/x-moz-place","uri":"https://mytts-info.ucoz.net/"},{"guid":"QdXYHl55HQnF","title":"ЛитРес","index":5,"dateAdded":1661409694101000,"lastModified":1661409712343000,"id":21,"typeCode":1,"iconUri":"https://www.litres.ru/static/litres/favicon.svg","type":"text/x-moz-place","uri":"https://www.litres.ru/"},{"guid":"KtDLHIy2hwA8","title":"Неолурк","index":6,"dateAdded":1668577158662000,"lastModified":1668577180588000,"id":22,"typeCode":1,"type":"text/x-moz-place","uri":"http://neolurk.org/wiki/%D0%97%D0%B0%D0%B3%D0%BB%D0%B0%D0%B2%D0%BD%D0%B0%D1%8F_%D1%81%D1%82%D1%80%D0%B0%D0%BD%D0%B8%D1%86%D0%B0"},{"guid":"6WRqRWPnD6A3","title":"Lurkmore | зеркало лурк","index":7,"dateAdded":1668577201622000,"lastModified":1668577216128000,"id":23,"typeCode":1,"type":"text/x-moz-place","uri":"http://lurklurk.com/"},{"guid":"zrGb8GRbtlIf","title":"Black Fire Pandemonium","index":8,"dateAdded":1698569982593000,"lastModified":1698569982593000,"id":145,"typeCode":1,"charset":"windows-1251","type":"text/x-moz-place","uri":"http://warrax.net/"},{"guid":"ysYu0SQ_hFKV","title":"Клуб любителей аудиокниг","index":9,"dateAdded":1701932418543000,"lastModified":1701932418543000,"id":150,"typeCode":1,"iconUri":"https://abook-club.ru/files/media/favicon_new.ico","type":"text/x-moz-place","uri":"https://abook-club.ru/"},{"guid":"oDRigG36SzSp","title":"Клуб АудиоКниг Форум","index":10,"dateAdded":1701932486050000,"lastModified":1701932607934000,"id":151,"typeCode":1,"charset":"windows-1251","type":"text/x-moz-place","uri":"https://abook-club.ru/forum/"}]},{"guid":"PAJyLE-2abNw","title":"Перевод","index":2,"dateAdded":1626842695535000,"lastModified":1627011884954000,"id":24,"typeCode":2,"type":"text/x-moz-place-container","children":[{"guid":"x70zJUCz0aSo","title":"Яндекс.Переводчик","index":0,"dateAdded":1626842712917000,"lastModified":1626842728594000,"id":25,"typeCode":1,"iconUri":"https://translate.yandex.ru/icons/favicon.png","type":"text/x-moz-place","uri":"https://translate.yandex.ru/"},{"guid":"69F77nCC0sXq","title":"Google Переводчик","index":1,"dateAdded":1626842738855000,"lastModified":1626842738855000,"id":26,"typeCode":1,"iconUri":"https://ssl.gstatic.com/translate/favicon.ico","type":"text/x-moz-place","uri":"https://translate.google.ru/"}]},{"guid":"NGCtPnLKLA_P","title":"Облака","index":3,"dateAdded":1626405273322000,"lastModified":1680845823404000,"id":27,"typeCode":2,"type":"text/x-moz-place-container","children":[{"guid":"jmEaSfPWpG-r","title":"Google Диск","index":0,"dateAdded":1626261008611000,"lastModified":1626405298857000,"id":28,"typeCode":1,"iconUri":"https://ssl.gstatic.com/docs/doclist/images/drive_2022q3_32dp.png","type":"text/x-moz-place","uri":"https://drive.google.com/drive/my-drive"},{"guid":"8PhB1G3K2mBb","title":"OneDrive","index":1,"dateAdded":1626414694518000,"lastModified":1626414874693000,"id":29,"typeCode":1,"iconUri":"https://p.sfx.ms/images/favicon.ico","type":"text/x-moz-place","uri":"https://onedrive.live.com/"},{"guid":"Z46jrLrTYgDE","title":"Dropbox","index":2,"dateAdded":1626414741247000,"lastModified":1626414741247000,"id":30,"typeCode":1,"iconUri":"https://cfl.dropboxstatic.com/static/metaserver/static/images/favicon.ico","type":"text/x-moz-place","uri":"https://www.dropbox.com/"},{"guid":"GGx9U8wZc3Pl","title":"Яндекс.Диск","index":3,"dateAdded":1626414765736000,"lastModified":1626414765736000,"id":31,"typeCode":1,"type":"text/x-moz-place","uri":"https://disk.yandex.ru/"},{"guid":"aGuP0S4wLYlR","title":"Облако Mail.ru","index":4,"dateAdded":1626414806662000,"lastModified":1626414827877000,"id":32,"typeCode":1,"iconUri":"https://cloud.imgsmail.ru/cloud.landings/208201/static/7e70f9b/landing/cloud-web/img/og/favicon.svg","type":"text/x-moz-place","uri":"https://cloud.mail.ru/"},{"guid":"WW6vF6ps1Mvs","title":"MEGA","index":5,"dateAdded":1626415800817000,"lastModified":1626415800817000,"id":33,"typeCode":1,"iconUri":"https://mega.io/wp-content/uploads/2023/01/m-logo.png","type":"text/x-moz-place","uri":"https://mega.io/"},{"guid":"QyHJsVgxODe6","title":"GitHub","index":6,"dateAdded":1680403001054000,"lastModified":1680403011038000,"id":126,"typeCode":1,"iconUri":"https://github.githubassets.com/favicons/favicon.svg","type":"text/x-moz-place","uri":"https://github.com/"}]},{"guid":"r-rTxdJ5tpHE","title":"Линукс","index":4,"dateAdded":1626175351065000,"lastModified":1698387332791000,"id":34,"typeCode":2,"type":"text/x-moz-place-container","children":[{"guid":"oWPd6ZHsWyZh","title":"debian","index":0,"dateAdded":1652596218508000,"lastModified":1654150348801000,"id":35,"typeCode":2,"type":"text/x-moz-place-container","children":[{"guid":"dvfBVjAyMUxh","title":"Debian","index":0,"dateAdded":1626234431338000,"lastModified":1652596287172000,"id":36,"typeCode":1,"type":"text/x-moz-place","uri":"https://www.debian.org/"},{"guid":"3OPxyCJJFzef","title":"Debian Wiki","index":1,"dateAdded":1652596581672000,"lastModified":1652596709986000,"id":37,"typeCode":1,"iconUri":"https://wiki.debian.org/htdocs/favicon.ico","type":"text/x-moz-place","uri":"https://wiki.debian.org/"},{"guid":"7YThNW-2dbhW","title":"Форум","index":2,"dateAdded":1652596646292000,"lastModified":1652596695975000,"id":38,"typeCode":1,"type":"text/x-moz-place","uri":"https://debianforum.ru/"},{"guid":"RHGWieK2JhfS","title":"Пакеты","index":3,"dateAdded":1652682632681000,"lastModified":1652682670082000,"id":39,"typeCode":1,"type":"text/x-moz-place","uri":"https://www.debian.org/distrib/packages"},{"guid":"3TbrE3QKUzry","title":"Manpages","index":4,"dateAdded":1652682580973000,"lastModified":1653879001895000,"id":40,"typeCode":1,"type":"text/x-moz-place","uri":"https://manpages.debian.org/"},{"guid":"lcKb2Cn_f9L2","title":"Ubuntu Manpage","index":5,"dateAdded":1628405449602000,"lastModified":1653878873509000,"id":41,"typeCode":1,"iconUri":"https://assets.ubuntu.com/v1/3361409d-apple-touch-icon-144x144-precomposed.png","type":"text/x-moz-place","uri":"http://manpages.ubuntu.com/"},{"guid":"uWdHipXzBREC","title":"OpenNet","index":6,"dateAdded":1626174515636000,"lastModified":1653878989790000,"id":42,"typeCode":1,"charset":"KOI8-R","iconUri":"https://www.opennet.ru/opennet_192tg.png","type":"text/x-moz-place","uri":"https://www.opennet.ru/"}]},{"guid":"gLWScV_BnwfX","title":"Arch","index":1,"dateAdded":1654149715822000,"lastModified":1698387332791000,"id":43,"typeCode":2,"type":"text/x-moz-place-container","children":[{"guid":"nO0By4KUAPU9","title":"Arch Linux","index":0,"dateAdded":1654149950261000,"lastModified":1654149960254000,"id":44,"typeCode":1,"iconUri":"https://archlinux.org/static/logos/apple-touch-icon-144x144.38cf584757c3.png","type":"text/x-moz-place","uri":"https://archlinux.org/"},{"guid":"MATt5_XmRXT-","title":"Русскоязычное Сообщество Arch Linux","index":1,"dateAdded":1654150186239000,"lastModified":1654150363550000,"id":45,"typeCode":1,"iconUri":"https://archlinux.org.ru/static/favicon.29302f683ff8.ico","type":"text/x-moz-place","uri":"https://archlinux.org.ru/"},{"guid":"8oa3r5k7gzoS","title":"ArchWiki","index":2,"dateAdded":1652667732207000,"lastModified":1654150377454000,"id":46,"typeCode":1,"type":"text/x-moz-place","uri":"https://wiki.archlinux.org/title/Main_page_(%D0%A0%D1%83%D1%81%D1%81%D0%BA%D0%B8%D0%B9)"},{"guid":"GABmqzvhyC8g","title":"Forum","index":3,"dateAdded":1654150205044000,"lastModified":1654150379576000,"id":47,"typeCode":1,"iconUri":"https://archlinux.org.ru/static/favicon.29302f683ff8.ico","type":"text/x-moz-place","uri":"https://archlinux.org.ru/forum/"},{"guid":"LhLlJJuEy4A1","title":"Arch manual pages","index":4,"dateAdded":1654150063367000,"lastModified":1654150063367000,"id":48,"typeCode":1,"iconUri":"https://man.archlinux.org/static/archlinux-common/favicon.29302f683ff8.ico","type":"text/x-moz-place","uri":"https://man.archlinux.org/"},{"guid":"14eUkvO24dDk","title":"BlackArch Linux","index":5,"dateAdded":1654150666446000,"lastModified":1654150685577000,"id":49,"typeCode":1,"iconUri":"https://blackarch.org/images/favicon.ico","type":"text/x-moz-place","uri":"https://blackarch.org/"},{"guid":"STVN8rFvYnPq","title":"Документация по BlackArch","index":6,"dateAdded":1654150706143000,"lastModified":1654150718174000,"id":50,"typeCode":1,"type":"text/x-moz-place","uri":"https://blackarch.ru/"},{"guid":"BZwZfpGvfDDV","title":"Package Search","index":7,"dateAdded":1654262255884000,"lastModified":1654262264555000,"id":51,"typeCode":1,"iconUri":"https://archlinux.org/static/logos/apple-touch-icon-144x144.38cf584757c3.png","type":"text/x-moz-place","uri":"https://archlinux.org/packages/"},{"guid":"MWdoIw8vyYUa","title":"AUR Packages","index":8,"dateAdded":1654565476835000,"lastModified":1654565501133000,"id":52,"typeCode":1,"iconUri":"https://aur.archlinux.org/static/images/favicon.ico","type":"text/x-moz-place","uri":"https://aur.archlinux.org/packages"},{"guid":"4-UNFyaHexVC","title":"Package Groups","index":9,"dateAdded":1654757417941000,"lastModified":1654757431628000,"id":53,"typeCode":1,"iconUri":"https://archlinux.org/static/logos/apple-touch-icon-144x144.38cf584757c3.png","type":"text/x-moz-place","uri":"https://archlinux.org/groups/x86_64/"},{"guid":"v-l-Myu0JFcq","title":"Все об Arch Linux","index":10,"dateAdded":1654915084323000,"lastModified":1654915084323000,"id":54,"typeCode":1,"iconUri":"https://ordanax.github.io/img/favicon.ico","type":"text/x-moz-place","uri":"https://ordanax.github.io/"},{"guid":"qgxKwYMuRePV","title":"Linux для себя","index":11,"dateAdded":1656039036481000,"lastModified":1656039049247000,"id":55,"typeCode":1,"type":"text/x-moz-place","uri":"https://lx4u.ru/"},{"guid":"6BwTrEyznLWC","title":"Руководство по оптимизации","index":12,"dateAdded":1658206902694000,"lastModified":1658206927451000,"id":56,"typeCode":1,"type":"text/x-moz-place","uri":"https://ventureo.codeberg.page/"},{"guid":"NJU9VG5j_rS6","title":"Arch based дистрибьютивы - 4PDA","index":13,"dateAdded":1658987850146000,"lastModified":1658987850146000,"id":57,"typeCode":1,"charset":"windows-1251","iconUri":"https://4pda.to/s/PXtiWkSWHhA0KqoNo3ICKdtT1fRG.svg","type":"text/x-moz-place","uri":"https://4pda.to/forum/index.php?showtopic=752345"},{"guid":"cq4YTZqB4mwR","title":"Arch Linux Repositories","index":14,"dateAdded":1669784430290000,"lastModified":1669784444821000,"id":58,"typeCode":1,"iconUri":"https://assets.pkgs.org/img/favicon.svg?v1","type":"text/x-moz-place","uri":"https://archlinux.pkgs.org/"}]},{"guid":"IYmNlGhteB2Y","title":"DistroWatch","index":2,"dateAdded":1653372977029000,"lastModified":1664171396845000,"id":59,"typeCode":1,"type":"text/x-moz-place","uri":"https://distrowatch.com/?language=RU"},{"guid":"85ysTRj2eX-B","title":"MX Linux","index":3,"dateAdded":1663121225299000,"lastModified":1663121265689000,"id":60,"typeCode":1,"iconUri":"https://mxlinux.org/wp-content/uploads/2023/06/cropped-android-chrome-512x512-1-192x192.png","type":"text/x-moz-place","uri":"https://mxlinux.org/"},{"guid":"fqJwWnyfknzL","title":"antiX","index":4,"dateAdded":1697340922818000,"lastModified":1697340955515000,"id":142,"typeCode":1,"iconUri":"https://antixlinux.com/wp-content/uploads/2017/03/logo_antiX.png","type":"text/x-moz-place","uri":"https://antixlinux.com/"},{"guid":"8wDNl0IbWafx","title":"Losst - Linux","index":5,"dateAdded":1626068130394000,"lastModified":1675391755059000,"id":61,"typeCode":1,"iconUri":"https://losst.pro/wp-content/uploads/2017/01/cropped-lt-192x192.png","type":"text/x-moz-place","uri":"https://losst.pro/"},{"guid":"5OS5DVZaWHua","title":"ZaLinux","index":6,"dateAdded":1630730935051000,"lastModified":1634365405833000,"id":62,"typeCode":1,"type":"text/x-moz-place","uri":"https://zalinux.ru/"},{"guid":"lzVRmcXU_SzX","title":"Пингвинус","index":7,"dateAdded":1680058971052000,"lastModified":1680058998451000,"id":125,"typeCode":1,"iconUri":"https://pingvinus.ru/themes/pingvinus3/images/favicons/apple-touch-icon-180x180.png","type":"text/x-moz-place","uri":"https://pingvinus.ru/"},{"guid":"D0ljooEE1D4S","title":"rus linux","index":8,"dateAdded":1627966482154000,"lastModified":1697597535063000,"id":65,"typeCode":1,"charset":"KOI8-R","type":"text/x-moz-place","uri":"http://rus-linux.net/"},{"guid":"9d3G0JpnOhhg","title":"Runtu","index":9,"dateAdded":1626181136514000,"lastModified":1697598540310000,"id":68,"typeCode":1,"iconUri":"https://runtu.org/images/favicon.ico","type":"text/x-moz-place","uri":"https://runtu.org/"},{"guid":"RvHb1iAPDAfJ","title":"Linux для начинающих","index":10,"dateAdded":1626174683992000,"lastModified":1637892401120000,"id":63,"typeCode":1,"iconUri":"https://zenway.ru/uploads/favicons/favicon-16x16.png","type":"text/x-moz-place","uri":"https://zenway.ru/"},{"guid":"x8jXZdBRuCvU","title":"Linux FAQ","index":11,"dateAdded":1626580065846000,"lastModified":1637892431311000,"id":64,"typeCode":1,"iconUri":"https://linux-faq.ru/thumb.php?src=e_MEDIA_IMAGE%2F2017-11%2Fsitelogo.jpg&aw=144&ah=144","type":"text/x-moz-place","uri":"https://linux-faq.ru/"},{"guid":"6Risb136pxzT","title":"LinuxSovet","index":12,"dateAdded":1663912866422000,"lastModified":1663913341356000,"id":66,"typeCode":1,"type":"text/x-moz-place","uri":"https://linuxoid85.github.io/LinuxSovet/"},{"guid":"wHctx_IdgZ2y","title":"Xubuntu.ru","index":13,"dateAdded":1626238792168000,"lastModified":1634365673589000,"id":67,"typeCode":1,"type":"text/x-moz-place","uri":"https://xubuntu-ru.net/"},{"guid":"Ak3F0XczCBMF","title":"Slax Linux","index":14,"dateAdded":1678771057665000,"lastModified":1697598610348000,"id":124,"typeCode":1,"type":"text/x-moz-place","uri":"https://slax.org.ru/"},{"guid":"BCibAKoq3DLw","title":"Slax","index":15,"dateAdded":1684309106183000,"lastModified":1684311073319000,"id":128,"typeCode":1,"type":"text/x-moz-place","uri":"https://www.slax.org/"},{"guid":"lNziHrZhfOAd","title":"Calculate Linux","index":16,"dateAdded":1684647205455000,"lastModified":1684647697485000,"id":129,"typeCode":1,"iconUri":"https://www.calculate-linux.org/assets/main/images/favicons/xapple-touch-icon-152x152.png.pagespeed.ic.Nngtwh9EKM.png","type":"text/x-moz-place","uri":"https://www.calculate-linux.org/"},{"guid":"VoZGhVuhgIan","title":"UALinux","index":17,"dateAdded":1626047269275000,"lastModified":1634365408921000,"id":69,"typeCode":1,"iconUri":"https://ualinux.com/templates/yoo_sun/apple_touch_icon.png","type":"text/x-moz-place","uri":"https://ualinux.com/ru/"},{"guid":"FBwbBOt9qu23","title":"Темы для xfce","index":18,"dateAdded":1626240041550000,"lastModified":1626240064791000,"id":70,"typeCode":1,"type":"text/x-moz-place","uri":"https://www.xfce-look.org/browse/"},{"guid":"na8bHJ4fdAfk","title":"Xfce Wiki","index":19,"dateAdded":1626240424278000,"lastModified":1626240433127000,"id":71,"typeCode":1,"type":"text/x-moz-place","uri":"https://wiki.xfce.org/ru/start"},{"guid":"d_aq_2rhb6BN","title":"doublecmd","index":20,"dateAdded":1626047386857000,"lastModified":1626318210576000,"id":72,"typeCode":1,"type":"text/x-moz-place","uri":"https://doublecmd.sourceforge.io/"},{"guid":"0ZXvvQW8q_vn","title":"Linux Mint Справочная информация","index":21,"dateAdded":1627011871940000,"lastModified":1627011884954000,"id":73,"typeCode":1,"type":"text/x-moz-place","uri":"https://onformix.blogspot.com/p/linuxmint.html"},{"guid":"Ss-s1JhZsc7I","title":"Говорящий Linux","index":22,"dateAdded":1627966327284000,"lastModified":1627966331875000,"id":74,"typeCode":1,"charset":"windows-1251","type":"text/x-moz-place","uri":"http://linux.tiflocomp.ru/"},{"guid":"1MBztq4AeOrh","title":"жизнь в консоли","index":23,"dateAdded":1628489754300000,"lastModified":1628489771394000,"id":75,"typeCode":1,"type":"text/x-moz-place","uri":"http://linux-bash.ru/"},{"guid":"NCjAYcDSpRIx","title":"Поиск Steam","index":24,"dateAdded":1629956081804000,"lastModified":1629956081804000,"id":76,"typeCode":1,"type":"text/x-moz-place","uri":"https://store.steampowered.com/search/?os=linux"}]},{"guid":"e_zzFWVukfq7","title":"Торренты","index":5,"dateAdded":1626175188234000,"lastModified":1701932550185000,"id":77,"typeCode":2,"type":"text/x-moz-place-container","children":[{"guid":"uM-ZJN30rVMz","title":"audioboo","index":0,"dateAdded":1626153359479000,"lastModified":1656047758804000,"id":78,"typeCode":1,"iconUri":"https://audioboo.org/templates/kinogoshik/images/logo.svg","type":"text/x-moz-place","uri":"https://audioboo.org/"},{"guid":"8Jf5hqz3TGWZ","title":"bitru","index":1,"dateAdded":1626153381536000,"lastModified":1626318169762000,"id":79,"typeCode":1,"iconUri":"https://bitru.org/styles/apple-touch-icon.png","type":"text/x-moz-place","uri":"https://bitru.org/"},{"guid":"m4nHcHU10hRS","title":"rutor.info","index":2,"dateAdded":1626265098527000,"lastModified":1626318127105000,"id":80,"typeCode":1,"iconUri":"http://cdnbunny.org/favicon.ico","type":"text/x-moz-place","uri":"http://rutor.info/"},{"guid":"5iA-Z1WUr8V8","title":"База Аудиокниг","index":3,"dateAdded":1626266669523000,"lastModified":1626318131120000,"id":81,"typeCode":1,"iconUri":"https://baza-knig.ru/templates/knigi/img/favicon.ico","type":"text/x-moz-place","uri":"https://baza-knig.ru/"},{"guid":"Wne5oQydfwkB","title":"a-booka","index":4,"dateAdded":1661319274878000,"lastModified":1661319666247000,"id":82,"typeCode":1,"type":"text/x-moz-place","uri":"https://a-booka.ru/"},{"guid":"7OZ4A2mR3zij","title":"RuTracker","index":5,"dateAdded":1627791817462000,"lastModified":1627792075792000,"id":83,"typeCode":1,"iconUri":"https://rutracker.org/favicon-16x16.png","type":"text/x-moz-place","uri":"http://rutracker.org/"},{"guid":"vM9JJfmA6KM-","title":"Metal Torrent Tracker","index":6,"dateAdded":1640927293424000,"lastModified":1640927321476000,"id":84,"typeCode":1,"iconUri":"https://www.metal-tracker.com/images/favicon.ico","type":"text/x-moz-place","uri":"https://www.metal-tracker.com/"},{"guid":"pHFFcbY0eEZw","title":"XXX Трекер","index":7,"dateAdded":1670986085059000,"lastModified":1670986108022000,"id":85,"typeCode":1,"type":"text/x-moz-place","uri":"https://xxxtor.com/"},{"guid":"okQFlUwfQQkC","title":"Клуб Любителей Аудиокниг","index":8,"dateAdded":1701932550185000,"lastModified":1701932622587000,"id":152,"typeCode":1,"charset":"windows-1251","type":"text/x-moz-place","uri":"http://torrent.abook-club.ru/"}]},{"guid":"rF1djOr_-vuL","title":"2ГИС","index":6,"dateAdded":1628393936573000,"lastModified":1628393972500000,"id":86,"typeCode":1,"type":"text/x-moz-place","uri":"https://2gis.ru/moscow"},{"guid":"0kUSIflcaxrX","title":"Озёрск","index":7,"dateAdded":1675489885186000,"lastModified":1694849854746000,"id":87,"typeCode":2,"type":"text/x-moz-place-container","children":[{"guid":"ar-9jOHLHjOh","title":"Озёрск.ru","index":0,"dateAdded":1675489953257000,"lastModified":1675489967400000,"id":88,"typeCode":1,"iconUri":"http://ozersk.ru/templates/ozersk_ru_2020/images/favicon.png","type":"text/x-moz-place","uri":"http://ozersk.ru/"},{"guid":"JrWXowsst5ZR","title":"Озерск 74","index":1,"dateAdded":1675490029022000,"lastModified":1675490041452000,"id":89,"typeCode":1,"charset":"windows-1251","type":"text/x-moz-place","uri":"https://www.ozersk74.ru/"},{"guid":"RetzNF81v6WZ","title":"Позитроника","index":2,"dateAdded":1675921254912000,"lastModified":1675921274811000,"id":90,"typeCode":1,"iconUri":"https://positronica.ru/local/templates/main_posi/img/favicons/favicon.svg","type":"text/x-moz-place","uri":"https://positronica.ru/"},{"guid":"WTSCZG63TPl7","title":"DNS","index":3,"dateAdded":1675921520308000,"lastModified":1675921534891000,"id":91,"typeCode":1,"iconUri":"https://cmp.dns-shop.ru/static/apple-icon-180x180.png","type":"text/x-moz-place","uri":"https://www.dns-shop.ru/"},{"guid":"cjRdqo5kRvUG","title":"Ситилинк","index":4,"dateAdded":1675921703180000,"lastModified":1675921712802000,"id":92,"typeCode":1,"type":"text/x-moz-place","uri":"https://www.citilink.ru/"},{"guid":"UyZO9CM5Nsfs","title":"Связной","index":5,"dateAdded":1675923344240000,"lastModified":1675923355754000,"id":93,"typeCode":1,"iconUri":"https://cdn.svyaznoy.ru/favicons/favicon-194x194.png?v=2","type":"text/x-moz-place","uri":"https://www.svyaznoy.ru/"},{"guid":"Cf2VeA9fwnN9","title":"RBT","index":6,"dateAdded":1676168792464000,"lastModified":1676168811157000,"id":94,"typeCode":1,"iconUri":"https://www.rbt.ru/img/favicon.ico","type":"text/x-moz-place","uri":"https://www.rbt.ru/"},{"guid":"atqWAtdLHS33","title":"НИКС","index":7,"dateAdded":1676169758964000,"lastModified":1676169768559000,"id":95,"typeCode":1,"charset":"windows-1251","iconUri":"https://www.nix.ru/favicon.svg","type":"text/x-moz-place","uri":"https://www.nix.ru/"},{"guid":"bD0zHjczWD0n","title":"Галамарт","index":8,"dateAdded":1689144424355000,"lastModified":1689144424355000,"id":132,"typeCode":1,"iconUri":"https://galamart.ru/assets/apple-touch-icon.png","type":"text/x-moz-place","uri":"https://galamart.ru/"},{"guid":"vaab0McS0rQW","title":"Wildberries","index":9,"dateAdded":1693974662167000,"lastModified":1693974927533000,"id":140,"typeCode":1,"type":"text/x-moz-place","uri":"https://www.wildberries.ru/"}]},{"guid":"dt5y4lA4t4cn","title":"tmp","index":8,"dateAdded":1652770681614000,"lastModified":1697613143548000,"id":97,"typeCode":2,"type":"text/x-moz-place-container","children":[{"guid":"fZqDPCeUyKKF","title":"Игорь Стрелков","index":0,"dateAdded":1652770654565000,"lastModified":1652770681941000,"id":98,"typeCode":1,"charset":"windows-1251","type":"text/x-moz-place","uri":"https://vk.com/igoristrelkov"},{"guid":"0AsmGdSwfOsf","title":"Александр Конторович","index":1,"dateAdded":1652770733947000,"lastModified":1652770733947000,"id":99,"typeCode":1,"charset":"windows-1251","iconUri":"https://vk.com/images/icons/pwa/apple/default.png?15","type":"text/x-moz-place","uri":"https://vk.com/id18085377"},{"guid":"a9nUc1cdjTjY","title":"Школа программирования","index":2,"dateAdded":1655784595528000,"lastModified":1655784616108000,"id":100,"typeCode":1,"iconUri":"https://progtips.ru/wp-content/uploads/2020/06/logo_progtips_figure150h.png","type":"text/x-moz-place","uri":"https://progtips.ru/"},{"guid":"Q7h1GuFFYfbR","title":"Алина Гросу","index":3,"dateAdded":1689236000665000,"lastModified":1689236000665000,"id":133,"typeCode":1,"charset":"windows-1251","iconUri":"https://vk.com/images/icons/pwa/apple/default.png?15","type":"text/x-moz-place","uri":"https://vk.com/a_grosu"},{"guid":"JHgT1ITI75aF","title":"Настя Каменских","index":4,"dateAdded":1690358817998000,"lastModified":1690358817998000,"id":134,"typeCode":1,"iconUri":"https://www.youtube.com/s/desktop/bd3558ba/img/favicon_144x144.png","type":"text/x-moz-place","uri":"https://www.youtube.com/@NKofficial/videos"},{"guid":"d6pjC2vXf7iQ","title":"PLAFON Канал о линуксе","index":5,"dateAdded":1690358938237000,"lastModified":1690358938237000,"id":135,"typeCode":1,"iconUri":"https://www.youtube.com/s/desktop/85bdacdc/img/favicon_144x144.png","type":"text/x-moz-place","uri":"https://www.youtube.com/@plafonlinux/videos"},{"guid":"kO4acXPQNmAm","title":"SHAMAN - YouTube","index":6,"dateAdded":1690612850940000,"lastModified":1690612850940000,"id":136,"typeCode":1,"iconUri":"https://www.youtube.com/s/desktop/bd3558ba/img/favicon_144x144.png","type":"text/x-moz-place","uri":"https://www.youtube.com/@SHAMAN_ME/videos"},{"guid":"UJvysPL9deCo","title":"Оля Полякова","index":7,"dateAdded":1692763812952000,"lastModified":1701406770281000,"id":137,"typeCode":1,"iconUri":"https://www.youtube.com/s/desktop/18a472b7/img/favicon_144x144.png","type":"text/x-moz-place","uri":"https://www.youtube.com/@PolyakovaOfficial/videos"},{"guid":"rd1HcBE0Wo76","title":"Юрий Мороз","index":8,"dateAdded":1693639516594000,"lastModified":1693639516594000,"id":138,"typeCode":1,"charset":"windows-1251","iconUri":"https://vk.com/images/icons/pwa/apple/default.png?15","type":"text/x-moz-place","uri":"https://vk.com/russmoroz"},{"guid":"Vf6KlRvD6v9L","title":"Диана Панченко","index":9,"dateAdded":1693715778270000,"lastModified":1693715778270000,"id":139,"typeCode":1,"iconUri":"https://static.cdninstagram.com/rsrc.php/v3/yI/r/VsNE-OHk_8a.png","type":"text/x-moz-place","uri":"https://www.instagram.com/dianapanchenko/"},{"guid":"niOcofpRLK3-","title":"Ксения Собчак","index":10,"dateAdded":1695196094767000,"lastModified":1695196094767000,"id":141,"typeCode":1,"iconUri":"https://static.cdninstagram.com/rsrc.php/v3/yI/r/VsNE-OHk_8a.png","type":"text/x-moz-place","uri":"https://www.instagram.com/xenia_sobchak/?hl=ru"},{"guid":"MVAosZPZM35E","title":"Pingvinus","index":11,"dateAdded":1697613143548000,"lastModified":1697613143548000,"id":143,"typeCode":1,"iconUri":"https://www.youtube.com/s/desktop/bd3558ba/img/favicon_144x144.png","type":"text/x-moz-place","uri":"https://www.youtube.com/@PingvinusIT/videos"}]}]},{"guid":"toolbar_____","title":"toolbar","index":1,"dateAdded":1676870616156000,"lastModified":1701009069259000,"id":3,"typeCode":2,"type":"text/x-moz-place-container","root":"toolbarFolder","children":[{"guid":"Ep_6oJohEUn0","title":"","index":0,"dateAdded":1688274085706000,"lastModified":1688274266063000,"id":131,"typeCode":1,"iconUri":"https://seo-fast.ru/css/img/web/apple-touch-icon-152x152.png","type":"text/x-moz-place","uri":"https://seo-fast.ru/"},{"guid":"3NzAzsNs7ZV1","title":"","index":1,"dateAdded":1626141800551000,"lastModified":1688274269159000,"id":101,"typeCode":1,"iconUri":"https://yandex.ru/pogoda/static/favicon.ico?v=3","type":"text/x-moz-place","uri":"https://yandex.ru/pogoda/ozersk"},{"guid":"x0KZWeIQugpj","title":"","index":2,"dateAdded":1676870616156000,"lastModified":1676870652273000,"id":102,"typeCode":1,"iconUri":"https://translate.yandex.ru/icons/favicon.png","type":"text/x-moz-place","uri":"https://translate.yandex.ru/"},{"guid":"SV_njSRXevUB","title":"","index":3,"dateAdded":1626142861030000,"lastModified":1676870405144000,"id":103,"typeCode":1,"iconUri":"https://www.youtube.com/s/desktop/85bdacdc/img/favicon_144x144.png","type":"text/x-moz-place","uri":"https://www.youtube.com/feed/subscriptions"},{"guid":"sj096CXXDQHl","title":"","index":4,"dateAdded":1701009056076000,"lastModified":1701009079558000,"id":149,"typeCode":1,"iconUri":"https://static.rutube.ru/static/img/favicon-icons/icon.svg","type":"text/x-moz-place","uri":"https://rutube.ru/"},{"guid":"E0Ros__-cYGf","title":"","index":5,"dateAdded":1626143134151000,"lastModified":1676870421672000,"id":104,"typeCode":1,"iconUri":"https://www.instagram.com/static/images/ico/favicon-192.png/68d99ba29cc8.png#tippytop","type":"text/x-moz-place","uri":"https://www.instagram.com/"},{"guid":"qJobiwf_9t7W","title":"","index":6,"dateAdded":1653026902656000,"lastModified":1676870424630000,"id":105,"typeCode":1,"iconUri":"https://static.xx.fbcdn.net/rsrc.php/yT/r/aGT3gskzWBf.ico","type":"text/x-moz-place","uri":"https://www.facebook.com/"},{"guid":"ZOK-oAXwvR0_","title":"","index":7,"dateAdded":1697870231812000,"lastModified":1697870245622000,"id":144,"typeCode":1,"iconUri":"https://ok.ru/res/i/apple-touch-icon_180-r.png","type":"text/x-moz-place","uri":"https://ok.ru/"},{"guid":"9KGpOcc1ZkYj","title":"","index":8,"dateAdded":1626588393733000,"lastModified":1694331676801000,"id":106,"typeCode":1,"type":"text/x-moz-place","uri":"https://bo.xhdporno.biz/"},{"guid":"HywI15dDPFOt","title":"","index":9,"dateAdded":1626146396337000,"lastModified":1676870430692000,"id":107,"typeCode":1,"iconUri":"https://github.githubassets.com/favicons/favicon.svg","type":"text/x-moz-place","uri":"https://github.com/yt-dlp/yt-dlp/blob/master/Changelog.md"},{"guid":"6qGvR2rd_2s_","title":"","index":10,"dateAdded":1626143919869000,"lastModified":1676870433212000,"id":108,"typeCode":1,"charset":"windows-1251","iconUri":"https://vk.com/images/icons/pwa/apple/default.png?15","type":"text/x-moz-place","uri":"https://vk.com/feed"},{"guid":"0O3yc1YeLcdX","title":"","index":11,"dateAdded":1626142657489000,"lastModified":1700630652377000,"id":109,"typeCode":1,"iconUri":"https://image.winudf.com/v2/upload/images/pwa_icon.png?w=152&q=100","type":"text/x-moz-place","uri":"https://m.apkpure.com/ru/"},{"guid":"tBHhNfjF9r9C","title":"","index":12,"dateAdded":1626142737242000,"lastModified":1676870439216000,"id":110,"typeCode":1,"charset":"windows-1251","iconUri":"https://4pda.to/s/PXtiWkSWHhA0KqoNo3ICKdtT1fRG.svg","type":"text/x-moz-place","uri":"https://4pda.to/forum/index.php?act=idx"},{"guid":"68BbfcBpS5_r","title":"","index":13,"dateAdded":1626152842168000,"lastModified":1676870443194000,"id":111,"typeCode":1,"charset":"windows-1251","type":"text/x-moz-place","uri":"http://www.koob.ru/"},{"guid":"wWCRzk3uKiOj","title":"","index":14,"dateAdded":1626152931011000,"lastModified":1676870445625000,"id":112,"typeCode":1,"iconUri":"https://au-ok.com/templates/au-ok/images/favicon.ico","type":"text/x-moz-place","uri":"https://au-ok.com/"},{"guid":"dhkB2oS1OMj6","title":"","index":15,"dateAdded":1699863059197000,"lastModified":1699863085696000,"id":146,"typeCode":1,"iconUri":"https://aume.ru/templates/aume/images/favicon.ico","type":"text/x-moz-place","uri":"https://aume.ru/"},{"guid":"dfSXHilovFso","title":"","index":16,"dateAdded":1626148527807000,"lastModified":1676870449072000,"id":113,"typeCode":1,"type":"text/x-moz-place","uri":"https://hackware.ru/"},{"guid":"4SBAC_vkw_hY","title":"","index":17,"dateAdded":1626588504481000,"lastModified":1676870451213000,"id":114,"typeCode":1,"charset":"KOI8-R","type":"text/x-moz-place","uri":"http://samlib.ru/l/lysak_s_w/"},{"guid":"6gSaRLlHaBKr","title":"","index":18,"dateAdded":1636867305098000,"lastModified":1676870453204000,"id":115,"typeCode":1,"iconUri":"https://apps.evozi.com/apk-downloader/assets/img/mini_icon.png","type":"text/x-moz-place","uri":"https://apps.evozi.com/apk-downloader/"},{"guid":"I3R7wzNbrQuj","title":"","index":19,"dateAdded":1639115577830000,"lastModified":1676870455796000,"id":116,"typeCode":1,"iconUri":"https://www.gstatic.com/android/market_images/web/favicon_v3.ico","type":"text/x-moz-place","uri":"https://play.google.com/store"},{"guid":"too0fiMWtmB9","title":"","index":20,"dateAdded":1639707140866000,"lastModified":1676870460065000,"id":117,"typeCode":1,"iconUri":"https://zozhnik.ru/wp-content/uploads/2020/09/cropped-logo_heart-192x192.jpg","type":"text/x-moz-place","uri":"https://zozhnik.ru/"},{"guid":"slWDPtKAqpgK","title":"","index":21,"dateAdded":1626588433091000,"lastModified":1676870959470000,"id":118,"typeCode":1,"iconUri":"https://cmtscience.ru/favicons/apple-touch-icon.png?v=1701149559","type":"text/x-moz-place","uri":"https://cmtscience.ru/"},{"guid":"EHfurwE92DR2","title":"","index":22,"dateAdded":1627965918940000,"lastModified":1676870961492000,"id":119,"typeCode":1,"iconUri":"https://cdn2.portableapps.com/apple-touch-icon.png","type":"text/x-moz-place","uri":"https://portableapps.com/ru"},{"guid":"vFiQqYyN7bQJ","title":"","index":23,"dateAdded":1626245603561000,"lastModified":1676870966149000,"id":120,"typeCode":1,"iconUri":"https://www.pochta.ru/icon-192x192.png","type":"text/x-moz-place","uri":"https://www.pochta.ru/tracking"},{"guid":"acRzAS63CsxF","title":"","index":24,"dateAdded":1674192842359000,"lastModified":1676870464002000,"id":121,"typeCode":1,"type":"text/x-moz-place","uri":"https://ru.savefrom.net/239/"},{"guid":"hiE3MIlqQ87J","title":"","index":25,"dateAdded":1680845743483000,"lastModified":1680845843114000,"id":127,"typeCode":1,"iconUri":"https://readovka.news/img/rus4/favicon.svg","type":"text/x-moz-place","uri":"https://readovka.news/"},{"guid":"C-rpmxX-qHNU","title":"","index":26,"dateAdded":1676170131171000,"lastModified":1694851105643000,"id":96,"typeCode":1,"iconUri":"https://www.ozon.ru/public/touch-icon-ipad-retina.png","type":"text/x-moz-place","uri":"https://www.ozon.ru/"},{"guid":"widKmFCfUgWK","title":"","index":27,"dateAdded":1700985580432000,"lastModified":1700985612749000,"id":148,"typeCode":1,"iconUri":"https://ru.drivemusic.me/apple-touch-icon.png","type":"text/x-moz-place","uri":"https://ru.drivemusic.me/"}]},{"guid":"unfiled_____","title":"unfiled","index":3,"dateAdded":1631588948409000,"lastModified":1631588948409000,"id":5,"typeCode":2,"type":"text/x-moz-place-container","root":"unfiledBookmarksFolder","children":[{"guid":"IedpqX6REen3","title":"Скачать книги fb2","index":0,"dateAdded":1631588948409000,"lastModified":1639797437706000,"id":122,"typeCode":1,"type":"text/x-moz-place","uri":"https://www-knigi.ru/"},{"guid":"i1YuzYiBJpgo","title":"Список FTP серверов","index":1,"dateAdded":1630475317693000,"lastModified":1639797462591000,"id":123,"typeCode":1,"type":"text/x-moz-place","uri":"https://scientifically.info/publ/7-1-0-52"}]},{"guid":"mobile______","title":"mobile","index":4,"dateAdded":1678289532117000,"lastModified":1678340601980000,"id":6,"typeCode":2,"type":"text/x-moz-place-container","root":"mobileFolder"}]}